{
    "official_name": "Nayoun Ham",
    "position": "Front-End Developer",
    "address": "Seoul, South Korea",
    "contact": "ellie.hahm0502@gmail",
  
    "dependencies": {
      "education": {
        "name": "Seoul Women's University",
        "major": "Inoformation Security, B.E",
        "graduate": "2020.08"
      },
      
      "Work Experience" : {
        "ATNS USA": {
          "period": "2019.07 - 2020.06",
          "position": "Intern/software developer"
        }, 
        "EarlySloth": {
          "period": "2021.01 - 2022.01",
          "position": "Junior Software developer/Front-End"
        },
        "Linkr": {
          "period": "2022.02 - To present",
          "position": "Software Developer"
        }
      },
      "skill": {
        "language": "English(Advanced) / Korean(Native)",
        "certificates": "Engineer Information Processing",
        "computer_language": "C++ | JavaScript | Java",
        "web": "HTML/CSS | Styled-Components | Sass | React | jQuery",
        "testing": "Cypress | Jest",
        "other" : "Git, Jenkins, AWS. Linux/Unix, Jira"
      },
      "extra": {
        "patents": {
          "Cloud server and method of managing image file": "10-2148937 | 10-2199335",
          "Inter-floor Noise Sensor with Arduino and Android": "10-2039820"
        }
      }
    }
  }